annex_dataproxy/__init__.py
annex_dataproxy/__main__.py
annex_dataproxy/_version.py
annex_dataproxy/cli.py
annex_dataproxy/remote.py
annex_dataproxy-1.0.0rc3.dist-info/METADATA
annex_dataproxy-1.0.0rc3.dist-info/WHEEL
annex_dataproxy-1.0.0rc3.dist-info/entry_points.txt
annex_dataproxy-1.0.0rc3.dist-info/RECORD
