Metadata-Version: 2.1
Name: annex-dataproxy
Version: 1.0.0rc3
Summary: git annex support for Ebrains Data Proxy
Author-email: Marmaduke Woodman <marmaduke.woodman@univ-amu.fr>
Classifier: Development Status :: 4 - Beta
Classifier: License :: OSI Approved :: Apache Software License
Classifier: Operating System :: OS Independent
Classifier: Programming Language :: Python :: 3
Requires-Dist: annexremote
Requires-Dist: requests
Provides-Extra: dev
Requires-Dist: build; extra == 'dev'
Requires-Dist: pytest; extra == 'dev'
Requires-Dist: twine; extra == 'dev'
